rf_humab/__init__.py
rf_humab/humanize_sequence.py
rf_humab/mapping.py
rf_humab/saved_models/__init__.py
rf_humab/saved_models/v1_model_all.sav
rf_humab/saved_models/v1_model_forced.sav
rf_humab/saved_models/v2_model_all.sav
rf_humab/saved_models/v2_model_forced.sav
rf_humab/saved_models/v3_model_all.sav
rf_humab/saved_models/v3_model_forced.sav
rf_humab/saved_models/v4_model_all.sav
rf_humab/saved_models/v4_model_forced.sav
rf_humab/saved_models/v5_model_all.sav
rf_humab/saved_models/v5_model_forced.sav
rf_humab/saved_models/v6_model_all.sav
rf_humab/saved_models/v6_model_forced.sav
rf_humab/saved_models/v7_model_all.sav
rf_humab/saved_models/v7_model_forced.sav
rf_humab/sequence_data/__init__.py
rf_humab/sequence_data/sample_sequences.csv
rf_humab-0.0.10.dist-info/METADATA
rf_humab-0.0.10.dist-info/WHEEL
rf_humab-0.0.10.dist-info/top_level.txt
rf_humab-0.0.10.dist-info/RECORD
