Metadata-Version: 2.4
Name: rf_humab
Version: 0.0.10
Summary: Humanization tool for IgG heavy chain sequences
Author: Lydia Stone
Author-email: <lstone@g.hmc.edu>
Keywords: python,first package
Classifier: Development Status :: 3 - Alpha
Classifier: Intended Audience :: Science/Research
Classifier: Programming Language :: Python :: 3
Classifier: Operating System :: MacOS :: MacOS X
Classifier: Operating System :: Microsoft :: Windows
Requires-Dist: numpy>=1.21.0
Requires-Dist: pandas>=1.3.0
Requires-Dist: scikit-learn>=1.0.0
Dynamic: author
Dynamic: author-email
Dynamic: classifier
Dynamic: description
Dynamic: keywords
Dynamic: requires-dist
Dynamic: summary
